gemini/__init__.py
gemini/basewebsocket.py
gemini/cached.py
gemini/debugly.py
gemini/marketdataws.py
gemini/order_book.py
gemini/ordereventsws.py
gemini/private_client.py
gemini/public_client.py
gemini_python-0.2.1.dist-info/LICENSE
gemini_python-0.2.1.dist-info/METADATA
gemini_python-0.2.1.dist-info/WHEEL
gemini_python-0.2.1.dist-info/top_level.txt
gemini_python-0.2.1.dist-info/RECORD
